vroompkg/__init__.py
vroompkg/__main__.py
vroompkg/detect.py
vroompkg/run5.py
vroompkg/data/defaultpic.png
vroompkg/data/deploy.prototxt.txt
vroompkg/data/res10_300x300_ssd_iter_140000.caffemodel
vroompkg/data/shape_predictor_68_face_landmarks.dat
vroompkg/data/smilepic.png
vroompkg/data/squintpic.png
vroompkg/data/widepic.png
vroompkg-0.0.15.dist-info/LICENSE
vroompkg-0.0.15.dist-info/METADATA
vroompkg-0.0.15.dist-info/WHEEL
vroompkg-0.0.15.dist-info/top_level.txt
vroompkg-0.0.15.dist-info/RECORD
