Metadata-Version: 2.1
Name: vroompkg
Version: 0.0.15
Summary: using machine learning to detect and improve engagement
Home-page: https://github.com/manasi-ganti/vroom
Author: Manasi Ganti
Author-email: manasi.ganti@gmail.com
License: UNKNOWN
Project-URL: Bug Tracker, https://github.com/manasi-ganti/vroom/issues
Platform: UNKNOWN
Classifier: Programming Language :: Python :: 3
Classifier: License :: OSI Approved :: MIT License
Classifier: Operating System :: OS Independent
Requires-Python: >=3.6
Requires-Dist: requests
Requires-Dist: dlib
Requires-Dist: imutils
Requires-Dist: matplotlib
Requires-Dist: numpy
Requires-Dist: opencv-python
Requires-Dist: scipy
